researchgpt/__init__.py
researchgpt/cli.py
researchgpt/config.py
researchgpt/main.py
researchgpt/modes.py
researchgpt/utils.py
researchgpt/writers/__init__.py
researchgpt/writers/base.py
researchgpt/writers/latex.py
researchgpt/writers/text.py
researchgpt-0.0.4.dist-info/METADATA
researchgpt-0.0.4.dist-info/WHEEL
researchgpt-0.0.4.dist-info/entry_points.txt
researchgpt-0.0.4.dist-info/top_level.txt
researchgpt-0.0.4.dist-info/RECORD
