Metadata-Version: 2.1
Name: researchgpt
Version: 0.0.4
Summary: Automated Research. Powered by LoopGPT.
